{
  "title": "The Pledge",
  "_year_data": "2001",
  "year": 2001,
  "rated": "R",
  "released": "2001-01-18T16:00:00.000Z",
  "runtime": "124 min",
  "genres": "Crime, Drama, Mystery",
  "director": "Sean Penn",
  "writer": "Friedrich Dürrenmatt (book), Jerzy Kromolowski (screenplay), Mary Olson-Kromolowski (screenplay)",
  "actors": "Patricia Clarkson, Beau Daniels, Benicio Del Toro, Dale Dickey",
  "plot": "The night he retires as a Nevada sheriff, Jerry Black pledges to the mother of a murdered girl that he will find the killer. Jerry doesn't believe the police arrested the right man; he discovers this is the third incident in the area in the recent past with victims young, blond, pretty, and small for their age. So he buys an old gas station in the mountains near the crimes in order to search for a tall man who drives a black station wagon, gives toy porcupines as gifts, and calls himself the wizard: clues from a drawing by the dead girl. Jerry's solitary life gives way to friendship with a woman and her small, blond daughter. Has Jerry neglected something that may prove fatal?",
  "languages": "English",
  "country": "USA",
  "awards": "1 win & 6 nominations.",
  "poster": "http://ia.media-imdb.com/images/M/MV5BMTYyMTQxNDA4OF5BMl5BanBnXkFtZTYwMjQ3NDk2._V1_SX300.jpg",
  "metascore": "71",
  "rating": "6.8",
  "votes": "42,786",
  "imdbid": "tt0237572",
  "type": "movie",
  "response": "True",
  "series": false,
  "imdburl": "https://www.imdb.com/title/tt0237572"
}