{
  "title": "The Isle",
  "_year_data": "2000",
  "year": 2000,
  "rated": "UNRATED",
  "released": "2000-04-21T16:00:00.000Z",
  "runtime": "90 min",
  "genres": "Drama, Thriller",
  "director": "Ki-duk Kim",
  "writer": "Ki-duk Kim",
  "actors": "Jung Suh, Yoosuk Kim, Sung-hee Park, Jae-hyeon Jo",
  "plot": "A Carer becomes the mother to a secluded isle.",
  "languages": "Korean",
  "country": "South Korea",
  "awards": "5 wins & 2 nominations.",
  "poster": "http://ia.media-imdb.com/images/M/MV5BMjEwMjgzNjEyNV5BMl5BanBnXkFtZTcwMTg0NDMzMQ@@._V1_SX300.jpg",
  "metascore": "61",
  "rating": "7.1",
  "votes": "10,077",
  "imdbid": "tt0255589",
  "type": "movie",
  "response": "True",
  "series": false,
  "imdburl": "https://www.imdb.com/title/tt0255589"
}