{
  "title": "Blue Spring",
  "_year_data": "2001",
  "year": 2001,
  "rated": "N/A",
  "released": "2002-06-28T16:00:00.000Z",
  "runtime": "83 min",
  "genres": "Drama",
  "director": "Toshiaki Toyoda",
  "writer": "Toshiaki Toyoda, Taiyô Matsumoto (comic strip)",
  "actors": "Ryûhei Matsuda, Hirofumi Arai, Sôsuke Takaoka, Yusuke Oshiba",
  "plot": "A group of a run-down Tokyo high school students face the struggles of growing up, growing apart from their friends and worrying about their future, while living in a highly violent environment.",
  "languages": "Japanese",
  "country": "Japan",
  "awards": "2 nominations.",
  "poster": "http://ia.media-imdb.com/images/M/MV5BMTUwNTUwOTUwMF5BMl5BanBnXkFtZTcwNTE1MzYyMQ@@._V1_SX300.jpg",
  "metascore": "N/A",
  "rating": "7.4",
  "votes": "2,444",
  "imdbid": "tt0309291",
  "type": "movie",
  "response": "True",
  "series": false,
  "imdburl": "https://www.imdb.com/title/tt0309291"
}