{
  "title": "The Kite Runner",
  "_year_data": "2007",
  "year": 2007,
  "rated": "PG-13",
  "released": "2008-01-10T16:00:00.000Z",
  "runtime": "128 min",
  "genres": "Drama",
  "director": "Marc Forster",
  "writer": "David Benioff (screenplay), Khaled Hosseini (novel)",
  "actors": "Khalid Abdalla, Atossa Leoni, Shaun Toub, Sayed Jafar Masihullah Gharibzada",
  "plot": "After spending years in California, Amir returns to his homeland in Afghanistan to help his old friend Hassan, whose son is in trouble.",
  "languages": "Dari, English, Pushto, Russian, Urdu",
  "country": "USA, China",
  "awards": "Nominated for 1 Oscar. Another 6 wins & 22 nominations.",
  "poster": "https://images-na.ssl-images-amazon.com/images/M/MV5BODcyNjY2MjEwM15BMl5BanBnXkFtZTcwODQ0MzI1MQ@@._V1_SX300.jpg",
  "metascore": "61",
  "rating": "7.6",
  "votes": "68,495",
  "imdbid": "tt0419887",
  "type": "movie",
  "response": "True",
  "series": false,
  "imdburl": "https://www.imdb.com/title/tt0419887"
}