{
  "title": "Chop Shop",
  "_year_data": "2007",
  "year": 2007,
  "rated": "UNRATED",
  "released": "2008-02-26T16:00:00.000Z",
  "runtime": "84 min",
  "genres": "Drama",
  "director": "Ramin Bahrani",
  "writer": "Bahareh Azimi, Ramin Bahrani",
  "actors": "Alejandro Polanco, Isamar Gonzales, Rob Sowulski, Carlos Zapata",
  "plot": "Alejandro, a resourceful street orphan on the verge of adolescence, lives and works in an auto-body repair shop in a sprawling junkyard on the outskirts of Queens, New York. In this chaotic world of adults, Alejandro struggles to make a better life for himself and his sixteen-year-old sister.",
  "languages": "English",
  "country": "USA",
  "awards": "4 wins & 7 nominations.",
  "poster": "https://images-na.ssl-images-amazon.com/images/M/MV5BMjE0ODUwNzk1MF5BMl5BanBnXkFtZTcwNzI2OTc1MQ@@._V1_SX300.jpg",
  "metascore": "83",
  "rating": "7.4",
  "votes": "3,575",
  "imdbid": "tt0990404",
  "type": "movie",
  "response": "True",
  "series": false,
  "imdburl": "https://www.imdb.com/title/tt0990404"
}