{
  "title": "Somers Town",
  "_year_data": "2008",
  "year": 2008,
  "rated": "N/A",
  "released": "2009-07-14T16:00:00.000Z",
  "runtime": "71 min",
  "genres": "Comedy, Drama",
  "director": "Shane Meadows",
  "writer": "Paul Fraser (original screenplay), Mother Vision (original idea)",
  "actors": "Thomas Turgoose, Ireneusz Czop, Piotr Jagiello, Perry Benson",
  "plot": "Two teenagers, both newcomers to London, forge an unlikely friendship over the course of a hot summer. Tomo is a runaway from Nottingham; Marek lives in the district of Somers Town, between King's Cross and Euston stations, where his dad is working on a new rail link. The boys are both infatuated with the same girl, and pass their days bickering over which of them loves her the most. Finding himself homeless, Tomo surreptitiously moves into Marek's bedroom - but it's only a matter of time before Marek's dad discovers what's going on...",
  "languages": "English, Polish, French",
  "country": "UK",
  "awards": "3 wins & 6 nominations.",
  "poster": "http://ia.media-imdb.com/images/M/MV5BMTI1Njg3MDg2Ml5BMl5BanBnXkFtZTcwNzcyNDA3Mg@@._V1_SX300.jpg",
  "metascore": "77",
  "rating": "6.9",
  "votes": "5,272",
  "imdbid": "tt1172206",
  "type": "movie",
  "response": "True",
  "series": false,
  "imdburl": "https://www.imdb.com/title/tt1172206"
}