{
  "title": "Borgman",
  "_year_data": "2013",
  "year": 2013,
  "rated": "NOT RATED",
  "released": "2013-08-28T16:00:00.000Z",
  "runtime": "113 min",
  "genres": "Drama, Thriller",
  "director": "Alex van Warmerdam",
  "writer": "Alex van Warmerdam",
  "actors": "Jan Bijvoet, Hadewych Minis, Jeroen Perceval, Alex van Warmerdam",
  "plot": "A vagrant enters the lives of an arrogant upper-class family, turning their lives into a psychological nightmare in the process.",
  "languages": "Dutch, English",
  "country": "Netherlands, Belgium, Denmark",
  "awards": "11 wins & 19 nominations.",
  "poster": "https://images-na.ssl-images-amazon.com/images/M/MV5BNDg5OTk0OTI3MF5BMl5BanBnXkFtZTgwMjYxMDM1MTE@._V1_SX300.jpg",
  "metascore": "66",
  "rating": "6.8",
  "votes": "11,848",
  "imdbid": "tt1954315",
  "type": "movie",
  "response": "True",
  "series": false,
  "imdburl": "https://www.imdb.com/title/tt1954315"
}