{
  "title": "Blue Ruin",
  "_year_data": "2013",
  "year": 2013,
  "rated": "R",
  "released": "2014-07-08T16:00:00.000Z",
  "runtime": "90 min",
  "genres": "Crime, Drama, Thriller",
  "director": "Jeremy Saulnier",
  "writer": "Jeremy Saulnier",
  "actors": "Macon Blair, Devin Ratray, Amy Hargreaves, Kevin Kolack",
  "plot": "A mysterious outsider's quiet life is turned upside down when he returns to his childhood home to carry out an act of vengeance. Proving himself an amateur assassin, he winds up in a brutal fight to protect his estranged family.",
  "languages": "English",
  "country": "USA, France",
  "awards": "7 wins & 15 nominations.",
  "poster": "https://images-na.ssl-images-amazon.com/images/M/MV5BMTY4NTM2MDg5OV5BMl5BanBnXkFtZTgwMDA3OTAwMTE@._V1_SX300.jpg",
  "metascore": "77",
  "rating": "7.1",
  "votes": "44,003",
  "imdbid": "tt2359024",
  "type": "movie",
  "response": "True",
  "series": false,
  "imdburl": "https://www.imdb.com/title/tt2359024"
}