{
  "title": "Before Night Falls",
  "_year_data": "2000",
  "year": 2000,
  "rated": "R",
  "released": "2001-02-22T16:00:00.000Z",
  "runtime": "133 min",
  "genres": "Biography, Drama",
  "director": "Julian Schnabel",
  "writer": "Cunningham O'Keefe, L치zaro G칩mez Carriles, Julian Schnabel, Reynaldo Arenas (memoir \"Before Night Falls\"), Jana Bokova (documentary \"Havana\")",
  "actors": "Olatz L칩pez Garmendia, Giovanni Florido, Lol칩 Navarro, Batan Silva",
  "plot": "Episodic look at the life of Cuban poet and novelist, Reinaldo Arenas (1943-1990), from his childhood in Oriente province to his death in New York City. He joins Castro's rebels. By 1964, ...",
  "languages": "English, Spanish, Russian, French",
  "country": "USA",
  "awards": "Nominated for 1 Oscar. Another 15 wins & 20 nominations.",
  "poster": "http://ia.media-imdb.com/images/M/MV5BMjE2MzIzMDI5OF5BMl5BanBnXkFtZTcwODYzMzMzMQ@@._V1_SX300.jpg",
  "metascore": "85",
  "rating": "7.3",
  "votes": "20,857",
  "imdbid": "tt0247196",
  "type": "movie",
  "response": "True",
  "series": false,
  "imdburl": "https://www.imdb.com/title/tt0247196"
}