{
  "title": "The Hobbit: The Battle of the Five Armies",
  "_year_data": "2014",
  "year": 2014,
  "rated": "PG-13",
  "released": "2014-12-16T16:00:00.000Z",
  "runtime": "144 min",
  "genres": "Adventure, Fantasy",
  "director": "Peter Jackson",
  "writer": "Fran Walsh (screenplay), Philippa Boyens (screenplay), Peter Jackson (screenplay), Guillermo del Toro (screenplay), J.R.R. Tolkien (novel)",
  "actors": "Ian McKellen, Martin Freeman, Richard Armitage, Ken Stott",
  "plot": "Bilbo and Company are forced to engage in a war against an array of combatants and keep the Lonely Mountain from falling into the hands of a rising darkness.",
  "languages": "English",
  "country": "New Zealand, USA",
  "awards": "Nominated for 1 Oscar. Another 6 wins & 45 nominations.",
  "poster": "https://images-na.ssl-images-amazon.com/images/M/MV5BODAzMDgxMDc1MF5BMl5BanBnXkFtZTgwMTI0OTAzMjE@._V1_SX300.jpg",
  "metascore": "59",
  "rating": "7.5",
  "votes": "359,869",
  "imdbid": "tt2310332",
  "type": "movie",
  "response": "True",
  "series": false,
  "imdburl": "https://www.imdb.com/title/tt2310332"
}