{
  "title": "Rams",
  "_year_data": "2015",
  "year": 2015,
  "rated": "R",
  "released": "2015-05-27T16:00:00.000Z",
  "runtime": "93 min",
  "genres": "Drama",
  "director": "Grímur Hákonarson",
  "writer": "Grímur Hákonarson",
  "actors": "Sigurður Sigurjónsson, Theodór Júlíusson, Charlotte Bøving, Jón Benónýsson",
  "plot": "In a remote Icelandic farming valley, two brothers who haven't spoken in 40 years have to come together in order to save what's dearest to them - their sheep.",
  "languages": "Icelandic",
  "country": "Iceland, Denmark, Norway, Poland",
  "awards": "28 wins & 8 nominations.",
  "poster": "https://images-na.ssl-images-amazon.com/images/M/MV5BNWI4MTg1OWMtZGQ0OC00Yzk3LTkwZDAtNzg1ZGFjZTExZTUzXkEyXkFqcGdeQXVyMzQ5Njc3OTg@._V1_SX300.jpg",
  "metascore": "N/A",
  "rating": "7.4",
  "votes": "5,712",
  "imdbid": "tt3296658",
  "type": "movie",
  "response": "True",
  "series": false,
  "imdburl": "https://www.imdb.com/title/tt3296658"
}