{
  "title": "The Second Mother",
  "_year_data": "2015",
  "year": 2015,
  "rated": "R",
  "released": "2015-08-27T16:00:00.000Z",
  "runtime": "112 min",
  "genres": "Comedy, Drama",
  "director": "Anna Muylaert",
  "writer": "Anna Muylaert",
  "actors": "Regina Casé, Michel Joelsas, Camila Márdila, Karine Teles",
  "plot": "Val spends 13 years working as nanny to Fabinho in São Paulo. She is financially stable but has to live with the guilt of having left her daughter Jéssica, in Pernambuco, in the northeast of Brazil, raised by relatives. As college entrance exams roll around, Jéssica wants to come to São Paulo to take her college entrance exams too. When Jéssica arrives, cohabitation is not easy. Everyone will be affected by the personality and candor of the girl and Val finds herself right in the middle of it.",
  "languages": "Portuguese",
  "country": "Brazil",
  "awards": "20 wins & 22 nominations.",
  "poster": "https://images-na.ssl-images-amazon.com/images/M/MV5BOTQ1NjIwMzcyNF5BMl5BanBnXkFtZTgwNDY0NzI1NjE@._V1_SX300.jpg",
  "metascore": "82",
  "rating": "7.9",
  "votes": "7,456",
  "imdbid": "tt3742378",
  "type": "movie",
  "response": "True",
  "series": false,
  "imdburl": "https://www.imdb.com/title/tt3742378"
}