{
  "title": "The Witch",
  "_year_data": "2015",
  "year": 2015,
  "rated": "R",
  "released": "2016-02-18T16:00:00.000Z",
  "runtime": "92 min",
  "genres": "Horror, Mystery",
  "director": "Robert Eggers",
  "writer": "Robert Eggers",
  "actors": "Anya Taylor-Joy, Ralph Ineson, Kate Dickie, Harvey Scrimshaw",
  "plot": "A family in 1630s New England is torn apart by the forces of witchcraft, black magic and possession.",
  "languages": "English",
  "country": "USA, UK, Canada, Brazil",
  "awards": "7 wins & 2 nominations.",
  "poster": "http://ia.media-imdb.com/images/M/MV5BMTY4MTU2NjMyNV5BMl5BanBnXkFtZTgwMzUwMDk4NzE@._V1_SX300.jpg",
  "metascore": "83",
  "rating": "6.7",
  "votes": "70,041",
  "imdbid": "tt4263482",
  "type": "movie",
  "response": "True",
  "series": false,
  "imdburl": "https://www.imdb.com/title/tt4263482"
}